pytechnicalindicators-3.0.5.dist-info/METADATA
pytechnicalindicators-3.0.5.dist-info/WHEEL
pytechnicalindicators-3.0.5.dist-info/licenses/LICENSE-MIT
pytechnicalindicators/__init__.py
pytechnicalindicators/pytechnicalindicators.cpython-311-aarch64-linux-gnu.so
pytechnicalindicators-3.0.5.dist-info/RECORD
