Metadata-Version: 2.4
Name: pytechnicalindicators
Version: 3.0.5
Classifier: Development Status :: 5 - Production/Stable
Classifier: Intended Audience :: Financial and Insurance Industry
Classifier: Topic :: Software Development :: Libraries
Classifier: Topic :: Office/Business :: Financial :: Investment
Classifier: License :: OSI Approved :: MIT License
Classifier: Programming Language :: Rust
Classifier: Programming Language :: Python :: 3
License-File: LICENSE-MIT
Summary: A collection of 60+ fully configurable technical indicators for financial analysis, powered by Rust and Python.
Keywords: finance,technical indicators,analysis,trading,python,rust,quantitative
Author-email: ChironMind <your@email.com>
Maintainer-email: ChironMind <your@email.com>
Requires-Python: >=3.10
Project-URL: Homepage, https://github.com/chironmind/PyTechnicalIndicators
Project-URL: Documentation, https://github.com/chironmind/PyTechnicalIndicators/wiki
Project-URL: Source, https://github.com/chironmind/PyTechnicalIndicators
Project-URL: Issues, https://github.com/chironmind/PyTechnicalIndicators/issues
